[
  {
    "Artikelnummer": "100076       ",
    "Suchbegriff": "EIN LOGITECH Cordless TouchPad T650, USB,2,4 GHz                                   ",
    "Anzahl": 1
  },
  {
    "Artikelnummer": "101013       ",
    "Suchbegriff": "POW VARTA AKKU Micro AAA, 2er Pack, Ni MH Akku 800mAh (Phone)                      ",
    "Anzahl": 2
  },
  {
    "Artikelnummer": "101384       ",
    "Suchbegriff": "POW ULTRON RealPower PB1700 solar, Taschenlampe, SOS Signal                        ",
    "Anzahl": 1
  },
  {
    "Artikelnummer": "101787       ",
    "Suchbegriff": "MEM SANDISK Ultra 64.0GB USB3.0-Stick                                              ",
    "Anzahl": 1
  },
  {
    "Artikelnummer": "102741       ",
    "Suchbegriff": "POW VARTA AKKU Micro AAA, 4er Pack, Ni MH Akku 1000mAh                             ",
    "Anzahl": 5
  },
  {
    "Artikelnummer": "103043       ",
    "Suchbegriff": "POW VARTA Batterien MaxTech AA 1,5V, 4er Pack.                                     ",
    "Anzahl": 2
  },
  {
    "Artikelnummer": "103469       ",
    "Suchbegriff": "KAB MICROSOFT Adapter, Miracast Wireless Display (WiDi), HDMI, USB,                ",
    "Anzahl": 1
  },
  {
    "Artikelnummer": "103890       ",
    "Suchbegriff": "SPK CABSTONE Soundstand, Wireless BlueTooth Lautsprecher, Stereo                   ",
    "Anzahl": 1
  },
  {
    "Artikelnummer": "103938       ",
    "Suchbegriff": "POW VARTA AKKU Mignon AA, 4er Pack, Ni MH Akku 2100mAh                             ",
    "Anzahl": 4
  },
  {
    "Artikelnummer": "104742       ",
    "Suchbegriff": "POW BIOS-Batterie, 3Volt, Typ:CR2032                                               ",
    "Anzahl": 9
  },
  {
    "Artikelnummer": "105129       ",
    "Suchbegriff": "POW VARTA PhonePower Mignon 2er Blister, AA, 1600 mAh, für Telefone                ",
    "Anzahl": 3
  },
  {
    "Artikelnummer": "107068       ",
    "Suchbegriff": "POW VARTA Batterien, Mini AAAA 1,5V, 2er Pack.                                     ",
    "Anzahl": 1
  },
  {
    "Artikelnummer": "108073       ",
    "Suchbegriff": "MEM CORSAIR Padlock3 32.0 GB USB3.0-Stick, Hardwareverschlüsselung,                ",
    "Anzahl": 1
  },
  {
    "Artikelnummer": "109731       ",
    "Suchbegriff": "MEM SANDISK Ultra 128.0GB USB3.0-Stick                                             ",
    "Anzahl": 2
  },
  {
    "Artikelnummer": "109799       ",
    "Suchbegriff": "POW VARTA Longlife Max Power, 9V-Blockbatterie                                     ",
    "Anzahl": 5
  },
  {
    "Artikelnummer": "1100380      ",
    "Suchbegriff": "MEM SANDISK Ultra, 32 GB, micro SDHC, m. Adapter, Class 10, bis 120 MB/s           ",
    "Anzahl": 1
  },
  {
    "Artikelnummer": "1100522      ",
    "Suchbegriff": "POW VARTA Longlife Batterien, Micro AAA 1,5V, 4er Pack.                            ",
    "Anzahl": 4
  },
  {
    "Artikelnummer": "1100701      ",
    "Suchbegriff": "POW VARTA Work Flex Aera Light inkl. 3 x AA Batterien                              ",
    "Anzahl": 2
  },
  {
    "Artikelnummer": "1100789      ",
    "Suchbegriff": "POW VARTA Longlife Batterien, D, 1,5V, 2er Pack.                                   ",
    "Anzahl": 1
  },
  {
    "Artikelnummer": "1100799      ",
    "Suchbegriff": "EIN REINERSCT CyberJack RFID basis                                                 ",
    "Anzahl": 1
  },
  {
    "Artikelnummer": "1101148      ",
    "Suchbegriff": "MEM SANDISK Ultra 256.0GB USB3.0-Stick                                             ",
    "Anzahl": 3
  },
  {
    "Artikelnummer": "1101364      ",
    "Suchbegriff": "MEM SANDISK Ultra Dual Drive Go, 64.0GB USB3.2 Gen 1, USB-A + USB-C                ",
    "Anzahl": 8
  },
  {
    "Artikelnummer": "1101365      ",
    "Suchbegriff": "MEM SANDISK Ultra Dual Drive Go, 128.0GB USB3.2 Gen 1, USB-A + USB-C               ",
    "Anzahl": 3
  },
  {
    "Artikelnummer": "1101458      ",
    "Suchbegriff": "MEM INTENSO 16 GB micro SDHC mit Adapter auf SD, Class 10 UHS-I                    ",
    "Anzahl": 1
  },
  {
    "Artikelnummer": "1101459      ",
    "Suchbegriff": "MEM SANDISK Ultra Dual Drive Luxe, 128.0GB USB3.2 Gen 1, USB-A + USB-C             ",
    "Anzahl": 1
  },
  {
    "Artikelnummer": "1101809      ",
    "Suchbegriff": "MEM SANDISK Ultra A1, 64 GB, micro SDXC, m.Adapter, Class 10, UHS-I,bis zu 140MB/s ",
    "Anzahl": 1
  },
  {
    "Artikelnummer": "1101810      ",
    "Suchbegriff": "MEM SANDISK Ultra A1, 128 GB, micro SDXC,m.Adapter,Class 10, UHS-I,bis zu 140MB/s  ",
    "Anzahl": 2
  },
  {
    "Artikelnummer": "110263       ",
    "Suchbegriff": "MEM MEDIARANGE MR908, 8.0GB, USB 2.0-Stick.                                        ",
    "Anzahl": 2
  },
  {
    "Artikelnummer": "111005       ",
    "Suchbegriff": "POW VARTA AKKU Endless Mignon AA, 4er Pack, Ni MH Akku 1000mAh                     ",
    "Anzahl": 2
  },
  {
    "Artikelnummer": "AK40-41-4800 ",
    "Suchbegriff": "POW Intenso Wireless Charger Alu + Fast Charge Adapter Qi, weiß                    ",
    "Anzahl": 1
  },
  {
    "Artikelnummer": "AK40-44-6099 ",
    "Suchbegriff": "ZUB 4SMARTS MyGuard Oberflächendesinfektion StaySafe                               ",
    "Anzahl": 35
  },
  {
    "Artikelnummer": "AK40-45-6768 ",
    "Suchbegriff": "POW VARTA Power Bank Energy 5.000mAh                                               ",
    "Anzahl": 2
  },
  {
    "Artikelnummer": "AK40-54-3842 ",
    "Suchbegriff": "POW VARTA Outdoor Ambiance L30RH                                                   ",
    "Anzahl": 2
  }
]
